edsnlp/package.py
edsnlp/reducers.py
edsnlp/patch_spacy.py
edsnlp/__init__.py
edsnlp/extensions.py
edsnlp/tune.py
edsnlp/language.py
edsnlp/train.py
edsnlp/evaluate.py
edsnlp/connectors/labeltool.py
edsnlp/connectors/brat.py
edsnlp/connectors/omop.py
edsnlp/connectors/__init__.py
edsnlp/metrics/__init__.py
edsnlp/metrics/ner.py
edsnlp/metrics/span_attribute.py
edsnlp/metrics/dep_parsing.py
edsnlp/core/__init__.py
edsnlp/core/torch_component.py
edsnlp/core/stream.py
edsnlp/core/pipeline.py
edsnlp/core/registries.py
edsnlp/processing/__init__.py
edsnlp/processing/deprecated_pipe.py
edsnlp/processing/spark.py
edsnlp/processing/simple.py
edsnlp/processing/multiprocessing.py
edsnlp/training/loggers.py
edsnlp/training/__init__.py
edsnlp/training/optimizer.py
edsnlp/training/trainer.py
edsnlp/resources/drugs.json
edsnlp/resources/AVC.csv.gz
edsnlp/resources/adicap.json.gz
edsnlp/resources/cim10.csv.gz
edsnlp/resources/verbs.csv.gz
edsnlp/utils/doc_to_text.py
edsnlp/utils/batching.py
edsnlp/utils/fuzzy_alignment.py
edsnlp/utils/spark_dtypes.py
edsnlp/utils/deprecation.py
edsnlp/utils/lazy_module.py
edsnlp/utils/__init__.py
edsnlp/utils/span_getters.py
edsnlp/utils/numbers.py
edsnlp/utils/stream_sentinels.py
edsnlp/utils/extensions.py
edsnlp/utils/collections.py
edsnlp/utils/examples.py
edsnlp/utils/bindings.py
edsnlp/utils/regex_utils.py
edsnlp/utils/filter.py
edsnlp/utils/resources.py
edsnlp/utils/typing.py
edsnlp/utils/file_system.py
edsnlp/utils/torch.py
edsnlp/utils/inclusion.py
edsnlp/pipes/terminations.py
edsnlp/pipes/__init__.py
edsnlp/pipes/base.py
edsnlp/pipes/misc/__init__.py
edsnlp/pipes/misc/split/__init__.py
edsnlp/pipes/misc/split/split.py
edsnlp/pipes/misc/tables/patterns.py
edsnlp/pipes/misc/tables/__init__.py
edsnlp/pipes/misc/tables/factory.py
edsnlp/pipes/misc/tables/tables.py
edsnlp/pipes/misc/sections/patterns.py
edsnlp/pipes/misc/sections/sections.py
edsnlp-0.20.0.dist-info/RECORD
edsnlp-0.20.0.dist-info/WHEEL
edsnlp-0.20.0.dist-info/entry_points.txt
edsnlp-0.20.0.dist-info/top_level.txt
edsnlp-0.20.0.dist-info/METADATA
edsnlp-0.20.0.dist-info/licenses/LICENSE
