Metadata-Version: 2.4
Name: edsnlp
Version: 0.20.0
Summary: Modular, fast NLP framework, compatible with Pytorch and spaCy, offering tailored support for French clinical notes.
Author-email: Data Science - DSN APHP <perceval.wajsburt@aphp.fr>
License: Copyright 2021 Assistance Publique - Hôpitaux de Paris
Project-URL: Source Code, https://github.com/aphp/edsnlp
Project-URL: Documentation, https://aphp.github.io/edsnlp
Project-URL: Demo, https://aphp.github.io/edsnlp/demo
Project-URL: Bug Tracker, https://github.com/aphp/edsnlp/issues
Requires-Python: >=3.10
License-File: LICENSE
Requires-Dist: loguru
Requires-Dist: pytz
Requires-Dist: pysimstring>=1.2.1
Requires-Dist: regex
Requires-Dist: spacy<4,>=3.8.7
Requires-Dist: confit>=0.9.0
Requires-Dist: tqdm
Requires-Dist: umls-downloader>=0.1.1
Requires-Dist: pandas>=1.4.0
Requires-Dist: typing-extensions>=4.0.0
Requires-Dist: dill
Requires-Dist: build>=1.0.0
Requires-Dist: toml
Requires-Dist: xxhash
Requires-Dist: pyarrow>=3.0.0
Requires-Dist: fsspec
Requires-Dist: pydantic>=2
Provides-Extra: ml
Requires-Dist: rich-logger>=0.3.1; extra == "ml"
Requires-Dist: torch>=2; extra == "ml"
Requires-Dist: foldedtensor>=0.4.0; extra == "ml"
Requires-Dist: safetensors>=0.3.0; extra == "ml"
Requires-Dist: transformers>=4.0.0; extra == "ml"
Requires-Dist: accelerate>=0.20.3; extra == "ml"
Dynamic: license-file
